CHANGES.txt
LICENSE.txt
MANIFEST.in
README.md
TODO.txt
pyproject.toml
setup.cfg
setup.py
tox.ini
src/facebook_utils/__init__.py
src/facebook_utils/api_urls.py
src/facebook_utils/api_versions.py
src/facebook_utils/core.py
src/facebook_utils/exceptions.py
src/facebook_utils/utils.py
src/facebook_utils.egg-info/PKG-INFO
src/facebook_utils.egg-info/SOURCES.txt
src/facebook_utils.egg-info/dependency_links.txt
src/facebook_utils.egg-info/not-zip-safe
src/facebook_utils.egg-info/requires.txt
src/facebook_utils.egg-info/top_level.txt
tests/__init__.py
tests/generate_credentials.py
tests/test_core.py