Metadata-Version: 2.4
Name: facebook_utils
Version: 0.60.0
Summary: Simple utilites for Facebook integration with your website.
Home-page: http://github.com/jvanasco/facebook_utils
Author: Jonathan Vanasco
Author-email: jonathan@findmeon.com
License: BSD
Keywords: facebook
Classifier: Programming Language :: Python
Classifier: Programming Language :: Python :: 3
Classifier: Framework :: Pyramid
Classifier: Intended Audience :: Developers
License-File: LICENSE.txt
Requires-Dist: requests>=1.2
Requires-Dist: typing_extensions
Provides-Extra: testing
Requires-Dist: mypy; extra == "testing"
Requires-Dist: pytest; extra == "testing"
Dynamic: author
Dynamic: author-email
Dynamic: classifier
Dynamic: description
Dynamic: description-content-type
Dynamic: home-page
Dynamic: keywords
Dynamic: license
Dynamic: license-file
Dynamic: provides-extra
Dynamic: requires-dist
Dynamic: summary
